DNA_Processing-0.0.3.data/data/requirements.txt
DNA_Processing-0.0.3.data/data/.git/config
dna_processing/__init__.py
DNA_Processing-0.0.3.dist-info/LICENSE
DNA_Processing-0.0.3.dist-info/METADATA
DNA_Processing-0.0.3.dist-info/WHEEL
DNA_Processing-0.0.3.dist-info/top_level.txt
DNA_Processing-0.0.3.dist-info/RECORD
